{
  "project_info": {
    "project_number": "178705499973",
    "firebase_url": "https://loaded-b2a62.firebaseio.com",
    "project_id": "loaded-b2a62",
    "storage_bucket": "loaded-b2a62.appspot.com"
  },
  "client": [
    {
      "client_info": {
        "mobilesdk_app_id": "1:178705499973:android:4bd4c93b887d81fa",
        "android_client_info": {
          "package_name": "app.com.loaded.android.loaded"
        }
      },
      "oauth_client": [
        {
          "client_id": "178705499973-0av4q118hgul9c62ngpjlfilmfq47bdg.apps.googleusercontent.com",
          "client_type": 3
        }
      ],
      "api_key": [
        {
          "current_key": "AIzaSyDhRd75UREaOdBa88-xDuCXTekQ2NJw1Rc"
        }
      ],
      "services": {
        "analytics_service": {
          "status": 1
        },
        "appinvite_service": {
          "status": 1,
          "other_platform_oauth_client": []
        },
        "ads_service": {
          "status": 2
        }
      }
    },
    {
      "client_info": {
        "mobilesdk_app_id": "1:178705499973:android:7f591b8cfc4ba2e4",
        "android_client_info": {
          "package_name": "app.com.loaded.android.stock"
        }
      },
      "oauth_client": [
        {
          "client_id": "178705499973-0av4q118hgul9c62ngpjlfilmfq47bdg.apps.googleusercontent.com",
          "client_type": 3
        }
      ],
      "api_key": [
        {
          "current_key": "AIzaSyDhRd75UREaOdBa88-xDuCXTekQ2NJw1Rc"
        }
      ],
      "services": {
        "analytics_service": {
          "status": 1
        },
        "appinvite_service": {
          "status": 1,
          "other_platform_oauth_client": []
        },
        "ads_service": {
          "status": 2
        }
      }
    }
  ],
  "configuration_version": "1"
}